job_farmer/__init__.py
job_farmer/farmer/__init__.py
job_farmer/farmer/farmer.py
job_farmer/job/__init__.py
job_farmer/job/jobconfiguration.py
job_farmer/log_pipe/__init__.py
job_farmer/log_pipe/log_pipe.py
job_farmer/system/__init__.py
job_farmer/system/nersc.py
job_farmer/system/system.py
job_farmer/task/__init__.py
job_farmer/task/task.py
job_farmer-0.1.8.data/scripts/job_runner
job_farmer-0.1.8.dist-info/LICENSE
job_farmer-0.1.8.dist-info/METADATA
job_farmer-0.1.8.dist-info/WHEEL
job_farmer-0.1.8.dist-info/top_level.txt
job_farmer-0.1.8.dist-info/RECORD
