Metadata-Version: 2.1
Name: job-farmer
Version: 0.1.8
Summary: A simple job farmer for HPC platforms
Home-page: https://gitlab.com/riffard/job_farmer
Author: Quentin Riffard
Author-email: quentin.riffard@gmail.com
License: GNU Affero General Public License v3.0
Project-URL: ReadTheDoc, https://riffard.gitlab.io/job_farmer/read_the_doc/
Project-URL: PyLint, https://riffard.gitlab.io/job_farmer/lint/
Project-URL: Coverage, https://riffard.gitlab.io/job_farmer/coverage/
Platform: UNKNOWN
License-File: LICENSE
Requires-Dist: coverage-badge (>=1.1.0)
Requires-Dist: pylint (>=2.14.3)
Requires-Dist: pylint-json2html (>=0.4.0)
Requires-Dist: pylint-gitlab (>=1.0.0)
Requires-Dist: pytest (>=7.1.2)
Requires-Dist: pytest-cov (>=3.0.0)
Requires-Dist: sphinx (>=5.0.2)
Requires-Dist: sphinx-rtd-theme (>=1.0.0)
